<?xml version="1.0" encoding="UTF-8"?>
<DEFECTS>
  <DEFECT>
    <SFA>
      <FILEPATH>C:\Users\33652\Desktop\Projet_ccp\ProjetCPPFinance\Projet_TD4\Projet_TD4\</FILEPATH>
      <FILENAME>CRRPricer_ClosedMethod.cpp</FILENAME>
      <LINE>6</LINE>
      <COLUMN>24</COLUMN>
    </SFA>
    <DEFECTCODE>26495</DEFECTCODE>
    <DESCRIPTION>La variable 'CRRPricer_ClosedMethod::_riskFreeRate' n'est pas initialisée. Initialisez toujours une variable membre (type.6).</DESCRIPTION>
    <FUNCTION>CRRPricer_ClosedMethod::{ctor}</FUNCTION>
    <DECORATED>??0CRRPricer_ClosedMethod@@QAE@XZ</DECORATED>
    <FUNCLINE>6</FUNCLINE>
    <ADDITIONALINFO>
      <targetSymbol>CRRPricer_ClosedMethod::_riskFreeRate</targetSymbol>
    </ADDITIONALINFO>
    <PATH></PATH>
  </DEFECT>
  <DEFECT>
    <SFA>
      <FILEPATH>C:\Users\33652\Desktop\Projet_ccp\ProjetCPPFinance\Projet_TD4\Projet_TD4\</FILEPATH>
      <FILENAME>CRRPricer_ClosedMethod.cpp</FILENAME>
      <LINE>6</LINE>
      <COLUMN>24</COLUMN>
    </SFA>
    <DEFECTCODE>26495</DEFECTCODE>
    <DESCRIPTION>La variable 'CRRPricer_ClosedMethod::_optionType' n'est pas initialisée. Initialisez toujours une variable membre (type.6).</DESCRIPTION>
    <FUNCTION>CRRPricer_ClosedMethod::{ctor}</FUNCTION>
    <DECORATED>??0CRRPricer_ClosedMethod@@QAE@XZ</DECORATED>
    <FUNCLINE>6</FUNCLINE>
    <ADDITIONALINFO>
      <targetSymbol>CRRPricer_ClosedMethod::_optionType</targetSymbol>
    </ADDITIONALINFO>
    <PATH></PATH>
  </DEFECT>
  <DEFECT>
    <SFA>
      <FILEPATH>C:\Users\33652\Desktop\Projet_ccp\ProjetCPPFinance\Projet_TD4\Projet_TD4\</FILEPATH>
      <FILENAME>CRRPricer_ClosedMethod.cpp</FILENAME>
      <LINE>12</LINE>
      <COLUMN>24</COLUMN>
    </SFA>
    <DEFECTCODE>26812</DEFECTCODE>
    <DESCRIPTION>Le type enum 'optionName’ est non délimité. Préférez ’enum class’ à ’enum' (enum.3).</DESCRIPTION>
    <FUNCTION>CRRPricer_ClosedMethod::{ctor}</FUNCTION>
    <DECORATED>??0CRRPricer_ClosedMethod@@QAE@NHNNNNW4optionName@@@Z</DECORATED>
    <FUNCLINE>12</FUNCLINE>
    <PATH></PATH>
  </DEFECT>
</DEFECTS>